{
  "entry_id": "na15-2021-na15-2021-const-184-1",
  "cycle_id": "na15-2021",
  "person": {
    "id": "person-5957d36fdf05",
    "full_name": "Giàng Thị Dùa",
    "full_name_folded": "giang thi dua",
    "dob": "16/6/1994",
    "gender": "Nữ",
    "nationality": "Việt Nam",
    "ethnicity": "Mông",
    "religion": "Không",
    "birthplace": "Xã Pá Lau, huyện Trạm Tấu, tỉnh Yên Bái",
    "current_residence": "Tổ dân phố số 2, thị trấn Trạm Tấu, huyện Trạm Tấu, tỉnh Yên Bái"
  },
  "entry": {
    "constituency_id": "na15-2021-const-184",
    "list_order": 1,
    "party_member_since": "08/6/2018",
    "is_na_delegate": "Không",
    "is_council_delegate": "Không"
  },
  "locality": {
    "id": "loc-9911d8be2ef2",
    "name_vi": "Tỉnh Yên Bái",
    "name_folded": "tinh yen bai",
    "type": "province_or_city"
  },
  "constituency": {
    "id": "na15-2021-const-184",
    "locality_id": "loc-9911d8be2ef2",
    "unit_number": 2,
    "seat_count": 3,
    "name_vi": "Đơn vị bầu cử số 2",
    "name_folded": "don vi bau cu so 2",
    "description": "Thị xã Nghĩa Lô, Huyện Văn Chấn, Huyện Trạm Tấu, Huyện Mù Cang Chải, Huyện Văn Yên",
    "unit_context_raw": "UBBC Tỉnh/Thành phố: Yên Bái Đơn vị bầu cử Số 2: Gồm thị xã Nghĩa Lộ và các huyện: Văn Chấn, Trạm Tấu, Mù Cang Chải, Văn Yên. Số đại biểu Quốc hội được bầu: 3 người. Số người ứng cử: 5 người.",
    "districts": [
      {
        "name_vi": "Huyện Mù Cang Chải",
        "name_folded": "huyen mu cang chai",
        "sources": [
          {
            "field": "congressional_units",
            "document_id": "doc-550cd8ad955d",
            "title": "Congressional units (PDF)",
            "url": "https://images.hcmcpv.org.vn/Uploads/File/280420219523F244/Danhsachbaucu-PYFO.pdf",
            "doc_type": "pdf",
            "published_date": null,
            "fetched_date": "2026-01-02",
            "notes": null
          }
        ]
      },
      {
        "name_vi": "Huyện Trạm Tấu",
        "name_folded": "huyen tram tau",
        "sources": [
          {
            "field": "congressional_units",
            "document_id": "doc-550cd8ad955d",
            "title": "Congressional units (PDF)",
            "url": "https://images.hcmcpv.org.vn/Uploads/File/280420219523F244/Danhsachbaucu-PYFO.pdf",
            "doc_type": "pdf",
            "published_date": null,
            "fetched_date": "2026-01-02",
            "notes": null
          }
        ]
      },
      {
        "name_vi": "Huyện Văn Chấn",
        "name_folded": "huyen van chan",
        "sources": [
          {
            "field": "congressional_units",
            "document_id": "doc-550cd8ad955d",
            "title": "Congressional units (PDF)",
            "url": "https://images.hcmcpv.org.vn/Uploads/File/280420219523F244/Danhsachbaucu-PYFO.pdf",
            "doc_type": "pdf",
            "published_date": null,
            "fetched_date": "2026-01-02",
            "notes": null
          }
        ]
      },
      {
        "name_vi": "Huyện Văn Yên",
        "name_folded": "huyen van yen",
        "sources": [
          {
            "field": "congressional_units",
            "document_id": "doc-550cd8ad955d",
            "title": "Congressional units (PDF)",
            "url": "https://images.hcmcpv.org.vn/Uploads/File/280420219523F244/Danhsachbaucu-PYFO.pdf",
            "doc_type": "pdf",
            "published_date": null,
            "fetched_date": "2026-01-02",
            "notes": null
          }
        ]
      },
      {
        "name_vi": "Thị xã Nghĩa Lô",
        "name_folded": "thi xa nghia lo",
        "sources": [
          {
            "field": "congressional_units",
            "document_id": "doc-550cd8ad955d",
            "title": "Congressional units (PDF)",
            "url": "https://images.hcmcpv.org.vn/Uploads/File/280420219523F244/Danhsachbaucu-PYFO.pdf",
            "doc_type": "pdf",
            "published_date": null,
            "fetched_date": "2026-01-02",
            "notes": null
          }
        ]
      }
    ],
    "sources": [
      {
        "field": "congressional_units",
        "document_id": "doc-550cd8ad955d",
        "title": "Congressional units (PDF)",
        "url": "https://images.hcmcpv.org.vn/Uploads/File/280420219523F244/Danhsachbaucu-PYFO.pdf",
        "doc_type": "pdf",
        "published_date": null,
        "fetched_date": "2026-01-02",
        "notes": null
      }
    ]
  },
  "attributes": [
    {
      "key": "education_academic_rank",
      "value": "Cử nhân"
    },
    {
      "key": "education_general",
      "value": "12/12"
    },
    {
      "key": "education_languages",
      "value": "Tiếng Anh B; nói được tiếng Mông"
    },
    {
      "key": "education_political",
      "value": "Trung cấp"
    },
    {
      "key": "education_professional",
      "value": "Đại học chuyên ngành luật"
    },
    {
      "key": "occupation_title",
      "value": "Chuyên viên Huyện đoàn Trạm Tấu, tỉnh Yên Bái"
    },
    {
      "key": "workplace",
      "value": "Huyện đoàn Trạm Tấu, tỉnh Yên Bái"
    }
  ],
  "sources": [
    {
      "field": "candidate_list",
      "document_id": "doc-d206c777cd70",
      "title": "Candidate list (PDF)",
      "url": "https://images.hcmcpv.org.vn/Uploads/File/280420219523F244/Danhsachbaucu-PYFO.pdf",
      "doc_type": "pdf",
      "published_date": null,
      "fetched_date": "2026-01-02",
      "notes": null
    }
  ],
  "changelog": []
}
